LICENSE
MANIFEST.in
README.rst
bootstrap.py
buildout.cfg
setup.py
versions.cfg
zinnia_mollom/__init__.py
zinnia_spam_checker_mollom.egg-info/PKG-INFO
zinnia_spam_checker_mollom.egg-info/SOURCES.txt
zinnia_spam_checker_mollom.egg-info/dependency_links.txt
zinnia_spam_checker_mollom.egg-info/not-zip-safe
zinnia_spam_checker_mollom.egg-info/requires.txt
zinnia_spam_checker_mollom.egg-info/top_level.txt