Metadata-Version: 1.1
Name: zinnia-spam-checker-mollom
Version: 1.0
Summary: Anti-spam protections for django-blog-zinnia with Mollom
Home-page: https://github.com/Fantomas42/zinnia-spam-checker-mollom
Author: Fantomas42
Author-email: fantomas42@gmail.com
License: BSD License
Keywords: django,zinnia,spam,mollom
Platform: UNKNOWN
Classifier: Framework :: Django
Classifier: Development Status :: 5 - Production/Stable
Classifier: Environment :: Web Environment
Classifier: Programming Language :: Python
Classifier: Intended Audience :: Developers
Classifier: Operating System :: OS Independent
Classifier: License :: OSI Approved :: BSD License
Classifier: Topic :: Software Development :: Libraries :: Python Modules
